cowpy/__init__.py
cowpy/cow.py
cowpy-1.1.5.dist-info/entry_points.txt
cowpy-1.1.5.dist-info/LICENSE.md
cowpy-1.1.5.dist-info/WHEEL
cowpy-1.1.5.dist-info/METADATA
cowpy-1.1.5.dist-info/RECORD
