Metadata-Version: 2.1
Name: cowpy
Version: 1.1.5
Summary: A cowsay clone for python in one file.
Home-page: https://github.com/jeffbuttars/cowpy
Author: Jeff Buttars
Author-email: jeffbuttars@gmail.com
License: Apache License 2.0
Platform: UNKNOWN
Classifier: Development Status :: 5 - Production/Stable
Classifier: Environment :: Console
Classifier: Intended Audience :: Developers
Classifier: License :: OSI Approved :: Apache Software License
Classifier: Operating System :: OS Independent
Classifier: Programming Language :: Python :: 3
Requires-Python: >=3.0
License-File: LICENSE.md
